zreprt/__init__.py
zreprt/__main__.py
zreprt/zreprt.py
zreprt-0.3.dist-info/METADATA
zreprt-0.3.dist-info/WHEEL
zreprt-0.3.dist-info/entry_points.txt
zreprt-0.3.dist-info/licenses/LICENSE
zreprt-0.3.dist-info/RECORD
