Metadata-Version: 2.1
Name: zreprt
Version: 0.3
Summary: ZAP-like reporting library
Project-URL: Issues, https://github.com/dast-one/zreprt/issues
Project-URL: Source, https://github.com/dast-one/zreprt
Author-email: Vital A Pi <code@vp.ag>
License: MIT License
License-File: LICENSE
Keywords: report,reporting,zap
Classifier: Development Status :: 4 - Beta
Classifier: License :: OSI Approved :: MIT License
Classifier: Operating System :: OS Independent
Classifier: Programming Language :: Python :: 3
Requires-Python: >=3.9
Requires-Dist: attrs
Requires-Dist: cattrs
Requires-Dist: python-dateutil
